dcentrapi/Base.py
dcentrapi/__init__.py
dcentrapi/constants.py
dcentrapi/eventPolling.py
dcentrapi/event_poller.py
dcentrapi/gasMonitor.py
dcentrapi/gas_fee_estimator.py
dcentrapi/hackMitigation.py
dcentrapi/merkleTree.py
dcentrapi/multi_chain_aggregator.py
dcentrapi/requests_dappi.py
dcentrapi/rpcAggregation.py
dcentrapi/rpc_aggregation_async.py
dcentrapi/rpc_aggregation_sync.py
dcentrapi/tokenPrices.py
dcentrapi/txSimulation.py
dcentrapi/utils.py
dcentrapi/abis/dcentral_helper.py
dcentrapi-0.6.1.dist-info/METADATA
dcentrapi-0.6.1.dist-info/WHEEL
dcentrapi-0.6.1.dist-info/licenses/LICENSE.rst
dcentrapi-0.6.1.dist-info/RECORD
