Metadata-Version: 2.4
Name: dcentrapi
Version: 0.6.1
Summary: Dcentralab Pypi packages
Author-email: "Dcentralab (Niv Shitrit)" <niv@dcentralab.com>
License: MIT
License-File: LICENSE.rst
Keywords: python
Classifier: Development Status :: 1 - Planning
Classifier: Intended Audience :: Developers
Classifier: Operating System :: MacOS :: MacOS X
Classifier: Operating System :: Microsoft :: Windows
Classifier: Operating System :: Unix
Classifier: Programming Language :: Python :: 3
Requires-Python: >=3.9
Requires-Dist: exceptiongroup>=1.0.0; python_version < '3.11'
Requires-Dist: requests==2.32.3
Requires-Dist: web3==7.11.1
Provides-Extra: test
Requires-Dist: aiohttp>=3.9.5; extra == 'test'
Requires-Dist: pytest-asyncio>=0.21.0; extra == 'test'
Requires-Dist: pytest-cov>=4.0.0; extra == 'test'
Requires-Dist: pytest-html>=3.1.0; extra == 'test'
Requires-Dist: pytest-xdist>=3.0.0; extra == 'test'
Requires-Dist: pytest>=7.0.0; extra == 'test'
